LICENSE
MANIFEST.in
README.md
README_ZH.md
setup.py
macast/.version
macast/__init__.py
macast/gui.py
macast/macast.py
macast/plugin.py
macast/renderer.py
macast/ssdp.py
macast/utils.py
macast.egg-info/PKG-INFO
macast.egg-info/SOURCES.txt
macast.egg-info/dependency_links.txt
macast.egg-info/entry_points.txt
macast.egg-info/requires.txt
macast.egg-info/top_level.txt
macast/assets/icon.icns
macast/assets/icon.ico
macast/assets/icon.png
macast/assets/menu_dark.png
macast/assets/menu_dark_large.png
macast/assets/menu_light.png
macast/assets/menu_light_large.png
macast/xml/AVTransport.xml
macast/xml/ConnectionManager.xml
macast/xml/Description.xml
macast/xml/RenderingControl.xml
macast/xml/SinkProtocolInfo.csv
macast_renderer/__init__.py
macast_renderer/mpv.py