Metadata-Version: 2.1
Name: macast
Version: 0.64
Summary: a DLNA Media Renderer
Home-page: https://github.com/xfangfang/Macast
Author: xfangfang
Author-email: xfangfang@126.com
License: GPL3
Keywords: mpv,dlna,renderer
Platform: MacOS X
Platform: Windows
Platform: POSIX
Classifier: Topic :: Multimedia :: Sound/Audio
Classifier: Topic :: Multimedia :: Video
Classifier: Programming Language :: Python :: 3
Classifier: Programming Language :: Python :: 3.6
Classifier: Programming Language :: Python :: 3.7
Classifier: Programming Language :: Python :: 3.8
Classifier: Programming Language :: Python :: 3.9
Classifier: Operating System :: MacOS :: MacOS X
Classifier: Operating System :: Microsoft :: Windows :: Windows NT/2000
Classifier: Operating System :: POSIX
Requires-Python: >=3.6
License-File: LICENSE
